repl_mcp.py
repl_mcp-0.1.0.dist-info/METADATA
repl_mcp-0.1.0.dist-info/WHEEL
repl_mcp-0.1.0.dist-info/entry_points.txt
repl_mcp-0.1.0.dist-info/licenses/LICENSE
repl_mcp-0.1.0.dist-info/RECORD
