Metadata-Version: 2.4
Name: repl-mcp
Version: 0.1.0
Summary: Interactive REPL for testing Model Context Protocol (MCP) servers
Project-URL: Homepage, https://github.com/kkokosa/repl-mcp
Project-URL: Repository, https://github.com/kkokosa/repl-mcp
Project-URL: Issues, https://github.com/kkokosa/repl-mcp/issues
Author: Konrad Kokosa
License: MIT License
License-File: LICENSE
Keywords: ai,mcp,model-context-protocol,repl,tools
Classifier: Development Status :: 4 - Beta
Classifier: Environment :: Console
Classifier: Intended Audience :: Developers
Classifier: License :: OSI Approved :: MIT License
Classifier: Programming Language :: Python :: 3
Classifier: Programming Language :: Python :: 3.10
Classifier: Programming Language :: Python :: 3.11
Classifier: Programming Language :: Python :: 3.12
Classifier: Topic :: Software Development :: Testing
Classifier: Topic :: Utilities
Requires-Python: >=3.10
Requires-Dist: mcp>=1.0.0
Requires-Dist: prompt-toolkit>=3.0.0
Requires-Dist: pydantic>=2.0.0
Requires-Dist: rich>=13.0.0
Provides-Extra: dev
Requires-Dist: pytest; extra == 'dev'
Requires-Dist: ruff; extra == 'dev'
Requires-Dist: tomli; (python_version < '3.11') and extra == 'dev'
Provides-Extra: yaml
Requires-Dist: pyyaml>=6.0; extra == 'yaml'
